azure/mgmt/digitaltwins/__init__.py
azure/mgmt/digitaltwins/_azure_digital_twins_management_client.py
azure/mgmt/digitaltwins/_configuration.py
azure/mgmt/digitaltwins/_patch.py
azure/mgmt/digitaltwins/_serialization.py
azure/mgmt/digitaltwins/_version.py
azure/mgmt/digitaltwins/py.typed
azure/mgmt/digitaltwins/aio/__init__.py
azure/mgmt/digitaltwins/aio/_azure_digital_twins_management_client.py
azure/mgmt/digitaltwins/aio/_configuration.py
azure/mgmt/digitaltwins/aio/_patch.py
azure/mgmt/digitaltwins/aio/operations/__init__.py
azure/mgmt/digitaltwins/aio/operations/_digital_twins_endpoint_operations.py
azure/mgmt/digitaltwins/aio/operations/_digital_twins_operations.py
azure/mgmt/digitaltwins/aio/operations/_operations.py
azure/mgmt/digitaltwins/aio/operations/_patch.py
azure/mgmt/digitaltwins/aio/operations/_private_endpoint_connections_operations.py
azure/mgmt/digitaltwins/aio/operations/_private_link_resources_operations.py
azure/mgmt/digitaltwins/aio/operations/_time_series_database_connections_operations.py
azure/mgmt/digitaltwins/models/__init__.py
azure/mgmt/digitaltwins/models/_azure_digital_twins_management_client_enums.py
azure/mgmt/digitaltwins/models/_models_py3.py
azure/mgmt/digitaltwins/models/_patch.py
azure/mgmt/digitaltwins/operations/__init__.py
azure/mgmt/digitaltwins/operations/_digital_twins_endpoint_operations.py
azure/mgmt/digitaltwins/operations/_digital_twins_operations.py
azure/mgmt/digitaltwins/operations/_operations.py
azure/mgmt/digitaltwins/operations/_patch.py
azure/mgmt/digitaltwins/operations/_private_endpoint_connections_operations.py
azure/mgmt/digitaltwins/operations/_private_link_resources_operations.py
azure/mgmt/digitaltwins/operations/_time_series_database_connections_operations.py
azure_mgmt_digitaltwins-7.0.0.dist-info/LICENSE
azure_mgmt_digitaltwins-7.0.0.dist-info/METADATA
azure_mgmt_digitaltwins-7.0.0.dist-info/WHEEL
azure_mgmt_digitaltwins-7.0.0.dist-info/top_level.txt
azure_mgmt_digitaltwins-7.0.0.dist-info/RECORD
